python_architecture_linter_cli/__init__.py
python_architecture_linter_cli/lint_command.py
python_architecture_linter_cli/steps.py
python_architecture_linter_cli-0.1.5.dist-info/METADATA
python_architecture_linter_cli-0.1.5.dist-info/WHEEL
python_architecture_linter_cli-0.1.5.dist-info/namespace_packages.txt
python_architecture_linter_cli-0.1.5.dist-info/top_level.txt
python_architecture_linter_cli-0.1.5.dist-info/RECORD
